youtubesearchpython/__init__.py
youtubesearchpython/extras.py
youtubesearchpython/search.py
youtubesearchpython/streamurlfetcher.py
youtubesearchpython/core/__init__.py
youtubesearchpython/core/channel.py
youtubesearchpython/core/channelsearch.py
youtubesearchpython/core/comments.py
youtubesearchpython/core/componenthandler.py
youtubesearchpython/core/constants.py
youtubesearchpython/core/exceptions.py
youtubesearchpython/core/hashtag.py
youtubesearchpython/core/playlist.py
youtubesearchpython/core/recommendations.py
youtubesearchpython/core/requests.py
youtubesearchpython/core/search.py
youtubesearchpython/core/streamurlfetcher.py
youtubesearchpython/core/suggestions.py
youtubesearchpython/core/transcript.py
youtubesearchpython/core/utils.py
youtubesearchpython/core/video.py
youtubesearchpython/future/__init__.py
youtubesearchpython/future/extras.py
youtubesearchpython/future/search.py
youtubesearchpython/future/streamurlfetcher.py
youtubesearchpython/handlers/componenthandler.py
youtubesearchpython/handlers/requesthandler.py
youtubesearchpython/legacy/__init__.py
yt_search_python-2.0.0.dist-info/licenses/LICENSE
yt_search_python-2.0.0.dist-info/METADATA
yt_search_python-2.0.0.dist-info/WHEEL
yt_search_python-2.0.0.dist-info/top_level.txt
yt_search_python-2.0.0.dist-info/RECORD
